Workbook

Sheet Raw_Data
A1: Order_ID | B1: Order_Date | C1: Customer_ID | D1: Customer_Name | E1: Category | F1: Product | G1: Quantity | H1: Unit_Price | I1: Discount_Percent | J1: Region | K1: Payment_Method | L1: Order_Status | M1: CLEAN REGION | N1: Gross_Sales | O1: Net_Sales | P1: Actual_Revenue | Q1: Discount_Amount | R1: Actual Discount
A2: ORD001 | B2: 46266 | C2: C001 | D2: Rahul Sharma | E2: Electronics | F2: Earbuds | G2: 2 | H2: 1200 | I2: 0.1 | J2: East | K2: UPI | L2: Delivered | M2: =PROPER(J2) -> East | N2: =G2*H2 -> 2400 | O2: =N2*(1-I2) -> 2160 | P2: =IF(L2="Delivered",O2,0) -> 2160 | Q2: =N2-O2 -> 240 | R2: =IF(L2="Delivered",Q2,0) -> 240
A3: ORD002 | B3: 46266 | C3: C002 | D3: Priya Singh | E3: Clothing | F3: T-Shirt | G3: 3 | H3: 600 | I3: 0.05 | J3: North | K3: Card | L3: Delivered | M3: =PROPER(J3) -> North | N3: =G3*H3 -> 1800 | O3: =N3*(1-I3) -> 1710 | P3: =IF(L3="Delivered",O3,0) -> 1710 | Q3: =N3-O3 -> 90 | R3: =IF(L3="Delivered",Q3,0) -> 90
A4: ORD003 | B4: 46267 | C4: C003 | D4: Amit Kumar | E4: Electronics | F4: Mouse | G4: 2 | H4: 800 | I4: 0 | J4: West | K4: UPI | L4: Delivered | M4: =PROPER(J4) -> West | N4: =G4*H4 -> 1600 | O4: =N4*(1-I4) -> 1600 | P4: =IF(L4="Delivered",O4,0) -> 1600 | Q4: =N4-O4 -> 0 | R4: =IF(L4="Delivered",Q4,0) -> 0
A5: ORD004 | B5: 46267 | C5: C004 | D5: Neha Das | E5: Home | F5: Lamp | G5: 1 | H5: 1500 | I5: 0.15 | J5: South | K5: COD | L5: Delivered | M5: =PROPER(J5) -> South | N5: =G5*H5 -> 1500 | O5: =N5*(1-I5) -> 1275 | P5: =IF(L5="Delivered",O5,0) -> 1275 | Q5: =N5-O5 -> 225 | R5: =IF(L5="Delivered",Q5,0) -> 225
A6: ORD005 | B6: 46268 | C6: C001 | D6: Rahul Sharma | E6: Clothing | F6: Jeans | G6: 1 | H6: 1800 | I6: 0.1 | J6: east | K6: Card | L6: Delivered | M6: =PROPER(J6) -> East | N6: =G6*H6 -> 1800 | O6: =N6*(1-I6) -> 1620 | P6: =IF(L6="Delivered",O6,0) -> 1620 | Q6: =N6-O6 -> 180 | R6: =IF(L6="Delivered",Q6,0) -> 180
A7: ORD006 | B7: 46269 | C7: C005 | D7: Riya Shah | E7: Electronics | F7: Keyboard | G7: 1 | H7: 2200 | I7: 0.05 | J7: West | K7: UPI | L7: Delivered | M7: =PROPER(J7) -> West | N7: =G7*H7 -> 2200 | O7: =N7*(1-I7) -> 2090 | P7: =IF(L7="Delivered",O7,0) -> 2090 | Q7: =N7-O7 -> 110 | R7: =IF(L7="Delivered",Q7,0) -> 110
A8: ORD007 | B8: 46269 | C8: C006 | D8: Karan Mehta | E8: Home | F8: Bedsheet | G8: 2 | H8: 900 | I8: 0 | J8: NORTH | K8: COD | L8: Delivered | M8: =PROPER(J8) -> North | N8: =G8*H8 -> 1800 | O8: =N8*(1-I8) -> 1800 | P8: =IF(L8="Delivered",O8,0) -> 1800 | Q8: =N8-O8 -> 0 | R8: =IF(L8="Delivered",Q8,0) -> 0
A9: ORD008 | B9: 46270 | C9: C007 | D9: Anjali Roy | E9: Beauty | F9: Face Wash | G9: 3 | H9: 350 | I9: 0.1 | J9: East | K9: UPI | L9: Cancelled | M9: =PROPER(J9) -> East | N9: =G9*H9 -> 1050 | O9: =N9*(1-I9) -> 945 | P9: =IF(L9="Delivered",O9,0) -> 0 | Q9: =N9-O9 -> 105 | R9: =IF(L9="Delivered",Q9,0) -> 0
A10: ORD009 | B10: 46271 | C10: C002 | D10: Priya Singh | E10: Electronics | F10: Power Bank | G10: 1 | H10: 1600 | I10: 0.05 | J10: North | K10: Card | L10: Delivered | M10: =PROPER(J10) -> North | N10: =G10*H10 -> 1600 | O10: =N10*(1-I10) -> 1520 | P10: =IF(L10="Delivered",O10,0) -> 1520 | Q10: =N10-O10 -> 80 | R10: =IF(L10="Delivered",Q10,0) -> 80
A11: ORD010 | B11: 46272 | C11: C008 | D11: Vikas Patel | E11: Clothing | F11: Shirt | G11: 2 | H11: 750 | I11: 0 | J11: West | K11: COD | L11: Returned | M11: =PROPER(J11) -> West | N11: =G11*H11 -> 1500 | O11: =N11*(1-I11) -> 1500 | P11: =IF(L11="Delivered",O11,0) -> 0 | Q11: =N11-O11 -> 0 | R11: =IF(L11="Delivered",Q11,0) -> 0
A12: ORD011 | B12: 46273 | C12: C009 | D12: Sneha Gupta | E12: Beauty | F12: Shampoo | G12: 2 | H12: 450 | I12: 0.1 | J12: South | K12: UPI | L12: Delivered | M12: =PROPER(J12) -> South | N12: =G12*H12 -> 900 | O12: =N12*(1-I12) -> 810 | P12: =IF(L12="Delivered",O12,0) -> 810 | Q12: =N12-O12 -> 90 | R12: =IF(L12="Delivered",Q12,0) -> 90
A13: ORD012 | B13: 46273 | C13: C010 | D13: Arjun Verma | E13: Home | F13: Wall Clock | G13: 1 | H13: 1100 | I13: 0.05 | J13: East | K13: Card | L13: Delivered | M13: =PROPER(J13) -> East | N13: =G13*H13 -> 1100 | O13: =N13*(1-I13) -> 1045 | P13: =IF(L13="Delivered",O13,0) -> 1045 | Q13: =N13-O13 -> 55 | R13: =IF(L13="Delivered",Q13,0) -> 55
... A16: ORD015 | B16: 46275 | C16: C012 | D16: Rohit Jain | E16: Electronics | F16: Charger | G16: 2 | H16: 700 | I16: 0.05 | J16: East | K16: UPI | L16: Delivered | M16: =PROPER(J16) -> East | N16: =G16*H16 -> 1400 | O16: =N16*(1-I16) -> 1330 | P16: =IF(L16="Delivered",O16,0) -> 1330 | Q16: =N16-O16 -> 70 | R16: =IF(L16="Delivered",Q16,0) -> 70

Sheet PIVOT_TABLE
A3: Customer_Name | B3: Count of Order_ID | D3: Region | E3: Sum of Actual_Revenue | G3: Category | H3: Sum of Quantity
A4: Amit Kumar | B4: 2 | D4: East | E4: 6155 | G4: Beauty | H4: 5
A5: Anjali Roy | B5: 1 | D5: North | E5: 5030 | G5: Clothing | H5: 8
A6: Arjun Verma | B6: 1 | D6: South | E6: 3795 | G6: Electronics | H6: 9
A7: Karan Mehta | B7: 1 | D7: West | E7: 4490 | G7: Home | H7: 4
A8: Neha Das | B8: 1 | D8: Grand Total | E8: 19470 | G8: Grand Total | H8: 26
A9: Pooja Sen | B9: 1
A10: Priya Singh | B10: 2
A11: Rahul Sharma | B11: 2 | D11: Category | E11: Sum of Actual_Revenue | G11: Payment_Method | H11: Sum of Actual_Revenue
A12: Riya Shah | B12: 1 | D12: Electronics | E12: 9500 | G12: Card | H12: 5895
A13: Rohit Jain | B13: 1 | D13: Clothing | E13: 5040 | G13: COD | H13: 4785
A14: Sneha Gupta | B14: 1 | D14: Home | E14: 4120 | G14: UPI | H14: 8790
A15: Vikas Patel | B15: 1 | D15: Beauty | E15: 810 | G15: Grand Total | H15: 19470
A16: Grand Total | B16: 15 | D16: Grand Total | E16: 19470
D18: Customer_Name | E18: Sum of Actual_Revenue
D19: Rahul Sharma | E19: 3780
D20: Priya Singh | E20: 3230
D21: Amit Kumar | E21: 2400
D22: Riya Shah | E22: 2090
D23: Karan Mehta | E23: 1800
D24: Grand Total | E24: 13300

Sheet KPI_SUMMARY
A1: Actual_Revenue | B1: =SUM(Raw_Data!P2:P16) -> 19470
A2: Total Orders | B2: =COUNTA(Raw_Data!A2:A16) -> 15
A3: Delivered Orders | B3: =COUNTIF(Raw_Data!L2:L16,"Delivered") -> 13
A4: Cancelled Orders | B4: =COUNTIF(Raw_Data!L2:L16,"Cancelled") -> 1
A5: Returned Orders | B5: =COUNTIF(Raw_Data!L2:L16,"Returned") -> 1
A6: Average Order Value | B6: =B1/B3 -> 1497.6923
A7: Delivery Rae | B7: =B3/B2 -> 0.86666667
A8: Cancellation Rate | B8: =B4/B2 -> 0.066666667
A9: Return Rate | B9: =B5/B2 -> 0.066666667
A10: Total Discount Given | B10: =SUM(Raw_Data!R2:R16) -> 1330
A11: GROSS SALES | B11: =B1+B10 -> 20800
A12: Order Success Rate | B12: =B3/B2 -> 0.86666667
A13: Repeat Customer | B13: =COUNTIF(PIVOT_TABLE!B4:B15,">1") -> 3
A14: UNIQUE CUSTOMER | B14: =COUNTA('[1]PIVOT TABLE'!A4:A15) -> 12
A15: Repeat Customer Rate | B15: =B13/B14 -> 0.25

Sheet Sales_Dashboard
B3: TOTAL REVENUE | F3: Total Orders | J3: Order Success Rate | N3: Average Order Value (AOV) | R3: Repeat Customer Rate
B4: =KPI_SUMMARY!B1 -> 19470 | F4: =KPI_SUMMARY!B2 -> 15 | J4: =KPI_SUMMARY!B12 -> 0.86666667 | N4: =KPI_SUMMARY!B6 -> 1497.6923 | R4: =KPI_SUMMARY!B15 -> 0.25
